{
  "annotations": {
    "changelogDate": "20250708151023"
  },
  "applications": ["magnus"],
  "documentation": "Accommodation catalog and templates",
  "dto": "mapstruct",
  "fields": [
    {
      "fieldName": "name",
      "fieldType": "String",
      "fieldValidateRules": ["required", "maxlength"],
      "fieldValidateRulesMaxlength": "100"
    },
    {
      "fieldName": "description",
      "fieldType": "TextBlob"
    },
    {
      "fieldName": "type",
      "fieldType": "AccommodationType",
      "fieldValidateRules": ["required"],
      "fieldValues": "SINGLE (Single room),DOUBLE (Double room),SUITE (Suite room),APARTMENT (Apartment rental),VILLA (Villa rental),HOSTEL (Hostel accommodation)"
    },
    {
      "fieldName": "pricePerNight",
      "fieldType": "BigDecimal",
      "fieldValidateRules": ["required", "min"],
      "fieldValidateRulesMin": "0"
    },
    {
      "fieldName": "costPerNight",
      "fieldType": "BigDecimal",
      "fieldValidateRules": ["min"],
      "fieldValidateRulesMin": "0"
    },
    {
      "fieldName": "maxOccupancy",
      "fieldType": "Integer",
      "fieldValidateRules": ["required", "min"],
      "fieldValidateRulesMin": "1"
    },
    {
      "fieldName": "address",
      "fieldType": "TextBlob"
    },
    {
      "fieldName": "amenities",
      "fieldType": "TextBlob"
    },
    {
      "fieldName": "checkInTime",
      "fieldType": "String",
      "fieldValidateRules": ["maxlength"],
      "fieldValidateRulesMaxlength": "10"
    },
    {
      "fieldName": "checkOutTime",
      "fieldType": "String",
      "fieldValidateRules": ["maxlength"],
      "fieldValidateRulesMaxlength": "10"
    },
    {
      "fieldName": "rating",
      "fieldType": "Double",
      "fieldValidateRules": ["min", "max"],
      "fieldValidateRulesMax": "5",
      "fieldValidateRulesMin": "0"
    },
    {
      "fieldName": "contactInfo",
      "fieldType": "TextBlob"
    },
    {
      "fieldName": "isActive",
      "fieldType": "Boolean",
      "fieldValidateRules": ["required"]
    },
    {
      "fieldName": "isTemplate",
      "fieldType": "Boolean",
      "fieldValidateRules": ["required"]
    },
    {
      "fieldName": "createdAt",
      "fieldType": "Instant",
      "fieldValidateRules": ["required"]
    },
    {
      "fieldName": "updatedAt",
      "fieldType": "Instant",
      "fieldValidateRules": ["required"]
    }
  ],
  "name": "Accommodation",
  "pagination": "pagination",
  "relationships": [],
  "searchEngine": "no",
  "service": "serviceImpl"
}
